[
    {
        "id": 1,
        "nombre":"Maceta 3D",
        "descripcion":"Maceta color marron",
        "precio": 4300,
        "descuento":5,
        "categoria":"en venta",
        "imagen":"producto1.jpg"
    },
    {
        "id": 2,
        "nombre":"Soporte vaso 3D",
        "descripcion":"soporte vaso para automovil",
        "precio": 6900,
        "descuento":10,
        "categoria":"en venta",
        "imagen":"producto2.jpg"
    },
    {
        "id": 3,
        "nombre":"Soporte Notebook 3D",
        "descripcion":"soporte notebook color naranja",
        "precio": 2100,
        "descuento":3,
        "categoria":"en venta",
        "imagen":"soporte1.jpg"
    },
    {
        "id": 4,
        "nombre":"Funda para celular 3D",
        "descripcion":"Fundas distintos modelos y colores",
        "precio": 1900,
        "descuento":0,
        "categoria":"en venta",
        "imagen":"FundaCelular3D.jpg"
    },
    {  
        "id": 5,
        "nombre":"Soporte Rollo de cocina 3D",
        "descripcion":"soporte rollo cocina varios colores",
        "precio": 1150,
        "descuento":5,
        "categoria":"en venta",
        "imagen":"SoporteRolloCocina3D.jpg"

    },
    {
        "id": 6,
        "nombre":"Abridor botellas 3D",
        "descripcion":"abridor botellas",
        "precio": 750,
        "descuento":3,
        "categoria":"en venta",
        "imagen":"AbridorBotellas3D.jpg"
    },
    {
        "id": 7,
        "nombre":"Soporte Notebook 3D",
        "descripcion":"soporte notebook color naranja",
        "precio": 2100,
        "descuento":3,
        "categoria":"en venta",
        "imagen":"ClipBolsasPlasticas3D.jpg"
    }
         ]